fsdem/__init__.py
fsdem/approx_func.py
fsdem/fsdem.py
fsdem/stability.py
fsdem-1.0.4.dist-info/METADATA
fsdem-1.0.4.dist-info/WHEEL
fsdem-1.0.4.dist-info/top_level.txt
fsdem-1.0.4.dist-info/RECORD
