Metadata-Version: 2.1
Name: fsdem
Version: 1.0.4
Summary: Feature Selection Dynamic Evaluation Metric
Home-page: https://github.com/mrajabinasab/FSDEM-Feature-Selection-Dynamic-Evaluation-Metric
Author: Muhammad Rajabinasab
Author-email: muhammad.rajabinasab@outlook.com
Classifier: Programming Language :: Python :: 3
Classifier: License :: OSI Approved :: MIT License
Classifier: Operating System :: OS Independent
Requires-Python: >=3.6
Requires-Dist: numpy
